Metadata-Version: 1.0
Name: ks-distributions
Version: 1.1
Summary: Gaussian And Binomial distributions
Home-page: UNKNOWN
Author: Kshitij Jagatkar
Author-email: kshitijjagatkar505@gmail.com
License: UNKNOWN
Platform: UNKNOWN
